term_assist/__init__.py
term_assist/main.py
term_assist/data/config_default.yaml
term_assist/data/models.yaml
term_assist/models/__init__.py
term_assist/models/anthropic_model.py
term_assist/models/model.py
term_assist/models/openai_model.py
term_assist/test/__init__.py
term_assist/test/base.py
term_assist/test/test.py
term_assist-0.6.1.dist-info/COPYING
term_assist-0.6.1.dist-info/METADATA
term_assist-0.6.1.dist-info/WHEEL
term_assist-0.6.1.dist-info/entry_points.txt
term_assist-0.6.1.dist-info/top_level.txt
term_assist-0.6.1.dist-info/RECORD
