Metadata-Version: 2.2
Name: term-assist
Version: 0.6.1
Summary: An AI assistant for your terminal.
Author-email: Logan Kirkland <logan@logankirk.land>
Maintainer-email: Logan Kirkland <logan@logankirk.land>
License:                     GNU AFFERO GENERAL PUBLIC LICENSE
Project-URL: Homepage, https://sr.ht/~logankirkland/term-assist/
Project-URL: Repository, https://git.sr.ht/~logankirkland/term-assist
Project-URL: Bug Tracker, https://todo.sr.ht/~logankirkland/term-assist
Project-URL: Mailing List, https://lists.sr.ht/~logankirkland/term-assist
Classifier: Programming Language :: Python :: 3
Classifier: License :: OSI Approved :: GNU Affero General Public License v3 or later (AGPLv3+)
Classifier: Operating System :: OS Independent
License-File: COPYING
Requires-Dist: annotated-types==0.7.0
Requires-Dist: anthropic==0.44.0
Requires-Dist: anyio==4.8.0
Requires-Dist: black==24.10.0
Requires-Dist: build==1.2.2.post1
Requires-Dist: certifi==2024.12.14
Requires-Dist: charset-normalizer==3.4.1
Requires-Dist: click==8.1.8
Requires-Dist: distro==1.9.0
Requires-Dist: docutils==0.21.2
Requires-Dist: filelock==3.17.0
Requires-Dist: fsspec==2024.12.0
Requires-Dist: h11==0.14.0
Requires-Dist: httpcore==1.0.7
Requires-Dist: httpx==0.28.1
Requires-Dist: huggingface-hub==0.27.1
Requires-Dist: id==1.5.0
Requires-Dist: idna==3.10
Requires-Dist: iniconfig==2.0.0
Requires-Dist: jaraco.classes==3.4.0
Requires-Dist: jaraco.context==6.0.1
Requires-Dist: jaraco.functools==4.1.0
Requires-Dist: jiter==0.8.2
Requires-Dist: keyboard==0.13.5
Requires-Dist: keyring==25.6.0
Requires-Dist: markdown-it-py==3.0.0
Requires-Dist: mdurl==0.1.2
Requires-Dist: more-itertools==10.6.0
Requires-Dist: mypy-extensions==1.0.0
Requires-Dist: nh3==0.2.20
Requires-Dist: openai==1.59.9
Requires-Dist: packaging==24.2
Requires-Dist: pathspec==0.12.1
Requires-Dist: platformdirs==4.3.6
Requires-Dist: pluggy==1.5.0
Requires-Dist: pydantic==2.10.5
Requires-Dist: pydantic_core==2.27.2
Requires-Dist: Pygments==2.19.1
Requires-Dist: pyobjc==11.0
Requires-Dist: pyobjc-core==11.0
Requires-Dist: pyobjc-framework-Accessibility==11.0
Requires-Dist: pyobjc-framework-Accounts==11.0
Requires-Dist: pyobjc-framework-AddressBook==11.0
Requires-Dist: pyobjc-framework-AdServices==11.0
Requires-Dist: pyobjc-framework-AdSupport==11.0
Requires-Dist: pyobjc-framework-AppleScriptKit==11.0
Requires-Dist: pyobjc-framework-AppleScriptObjC==11.0
Requires-Dist: pyobjc-framework-ApplicationServices==11.0
Requires-Dist: pyobjc-framework-AppTrackingTransparency==11.0
Requires-Dist: pyobjc-framework-AudioVideoBridging==11.0
Requires-Dist: pyobjc-framework-AuthenticationServices==11.0
Requires-Dist: pyobjc-framework-AutomaticAssessmentConfiguration==11.0
Requires-Dist: pyobjc-framework-Automator==11.0
Requires-Dist: pyobjc-framework-AVFoundation==11.0
Requires-Dist: pyobjc-framework-AVKit==11.0
Requires-Dist: pyobjc-framework-AVRouting==11.0
Requires-Dist: pyobjc-framework-BackgroundAssets==11.0
Requires-Dist: pyobjc-framework-BrowserEngineKit==11.0
Requires-Dist: pyobjc-framework-BusinessChat==11.0
Requires-Dist: pyobjc-framework-CalendarStore==11.0
Requires-Dist: pyobjc-framework-CallKit==11.0
Requires-Dist: pyobjc-framework-Carbon==11.0
Requires-Dist: pyobjc-framework-CFNetwork==11.0
Requires-Dist: pyobjc-framework-Cinematic==11.0
Requires-Dist: pyobjc-framework-ClassKit==11.0
Requires-Dist: pyobjc-framework-CloudKit==11.0
Requires-Dist: pyobjc-framework-Cocoa==11.0
Requires-Dist: pyobjc-framework-Collaboration==11.0
Requires-Dist: pyobjc-framework-ColorSync==11.0
Requires-Dist: pyobjc-framework-Contacts==11.0
Requires-Dist: pyobjc-framework-ContactsUI==11.0
Requires-Dist: pyobjc-framework-CoreAudio==11.0
Requires-Dist: pyobjc-framework-CoreAudioKit==11.0
Requires-Dist: pyobjc-framework-CoreBluetooth==11.0
Requires-Dist: pyobjc-framework-CoreData==11.0
Requires-Dist: pyobjc-framework-CoreHaptics==11.0
Requires-Dist: pyobjc-framework-CoreLocation==11.0
Requires-Dist: pyobjc-framework-CoreMedia==11.0
Requires-Dist: pyobjc-framework-CoreMediaIO==11.0
Requires-Dist: pyobjc-framework-CoreMIDI==11.0
Requires-Dist: pyobjc-framework-CoreML==11.0
Requires-Dist: pyobjc-framework-CoreMotion==11.0
Requires-Dist: pyobjc-framework-CoreServices==11.0
Requires-Dist: pyobjc-framework-CoreSpotlight==11.0
Requires-Dist: pyobjc-framework-CoreText==11.0
Requires-Dist: pyobjc-framework-CoreWLAN==11.0
Requires-Dist: pyobjc-framework-CryptoTokenKit==11.0
Requires-Dist: pyobjc-framework-DataDetection==11.0
Requires-Dist: pyobjc-framework-DeviceCheck==11.0
Requires-Dist: pyobjc-framework-DeviceDiscoveryExtension==11.0
Requires-Dist: pyobjc-framework-DictionaryServices==11.0
Requires-Dist: pyobjc-framework-DiscRecording==11.0
Requires-Dist: pyobjc-framework-DiscRecordingUI==11.0
Requires-Dist: pyobjc-framework-DiskArbitration==11.0
Requires-Dist: pyobjc-framework-DVDPlayback==11.0
Requires-Dist: pyobjc-framework-EventKit==11.0
Requires-Dist: pyobjc-framework-ExceptionHandling==11.0
Requires-Dist: pyobjc-framework-ExecutionPolicy==11.0
Requires-Dist: pyobjc-framework-ExtensionKit==11.0
Requires-Dist: pyobjc-framework-ExternalAccessory==11.0
Requires-Dist: pyobjc-framework-FileProvider==11.0
Requires-Dist: pyobjc-framework-FileProviderUI==11.0
Requires-Dist: pyobjc-framework-FinderSync==11.0
Requires-Dist: pyobjc-framework-FSEvents==11.0
Requires-Dist: pyobjc-framework-GameCenter==11.0
Requires-Dist: pyobjc-framework-GameController==11.0
Requires-Dist: pyobjc-framework-GameKit==11.0
Requires-Dist: pyobjc-framework-GameplayKit==11.0
Requires-Dist: pyobjc-framework-HealthKit==11.0
Requires-Dist: pyobjc-framework-ImageCaptureCore==11.0
Requires-Dist: pyobjc-framework-InputMethodKit==11.0
Requires-Dist: pyobjc-framework-InstallerPlugins==11.0
Requires-Dist: pyobjc-framework-InstantMessage==11.0
Requires-Dist: pyobjc-framework-Intents==11.0
Requires-Dist: pyobjc-framework-IntentsUI==11.0
Requires-Dist: pyobjc-framework-IOBluetooth==11.0
Requires-Dist: pyobjc-framework-IOBluetoothUI==11.0
Requires-Dist: pyobjc-framework-IOSurface==11.0
Requires-Dist: pyobjc-framework-iTunesLibrary==11.0
Requires-Dist: pyobjc-framework-KernelManagement==11.0
Requires-Dist: pyobjc-framework-LatentSemanticMapping==11.0
Requires-Dist: pyobjc-framework-LaunchServices==11.0
Requires-Dist: pyobjc-framework-libdispatch==11.0
Requires-Dist: pyobjc-framework-libxpc==11.0
Requires-Dist: pyobjc-framework-LinkPresentation==11.0
Requires-Dist: pyobjc-framework-LocalAuthentication==11.0
Requires-Dist: pyobjc-framework-LocalAuthenticationEmbeddedUI==11.0
Requires-Dist: pyobjc-framework-MailKit==11.0
Requires-Dist: pyobjc-framework-MapKit==11.0
Requires-Dist: pyobjc-framework-MediaAccessibility==11.0
Requires-Dist: pyobjc-framework-MediaExtension==11.0
Requires-Dist: pyobjc-framework-MediaLibrary==11.0
Requires-Dist: pyobjc-framework-MediaPlayer==11.0
Requires-Dist: pyobjc-framework-MediaToolbox==11.0
Requires-Dist: pyobjc-framework-Metal==11.0
Requires-Dist: pyobjc-framework-MetalFX==11.0
Requires-Dist: pyobjc-framework-MetalKit==11.0
Requires-Dist: pyobjc-framework-MetalPerformanceShaders==11.0
Requires-Dist: pyobjc-framework-MetalPerformanceShadersGraph==11.0
Requires-Dist: pyobjc-framework-MetricKit==11.0
Requires-Dist: pyobjc-framework-MLCompute==11.0
Requires-Dist: pyobjc-framework-ModelIO==11.0
Requires-Dist: pyobjc-framework-MultipeerConnectivity==11.0
Requires-Dist: pyobjc-framework-NaturalLanguage==11.0
Requires-Dist: pyobjc-framework-NetFS==11.0
Requires-Dist: pyobjc-framework-Network==11.0
Requires-Dist: pyobjc-framework-NetworkExtension==11.0
Requires-Dist: pyobjc-framework-NotificationCenter==11.0
Requires-Dist: pyobjc-framework-OpenDirectory==11.0
Requires-Dist: pyobjc-framework-OSAKit==11.0
Requires-Dist: pyobjc-framework-OSLog==11.0
Requires-Dist: pyobjc-framework-PassKit==11.0
Requires-Dist: pyobjc-framework-PencilKit==11.0
Requires-Dist: pyobjc-framework-PHASE==11.0
Requires-Dist: pyobjc-framework-Photos==11.0
Requires-Dist: pyobjc-framework-PhotosUI==11.0
Requires-Dist: pyobjc-framework-PreferencePanes==11.0
Requires-Dist: pyobjc-framework-PushKit==11.0
Requires-Dist: pyobjc-framework-Quartz==11.0
Requires-Dist: pyobjc-framework-QuickLookThumbnailing==11.0
Requires-Dist: pyobjc-framework-ReplayKit==11.0
Requires-Dist: pyobjc-framework-SafariServices==11.0
Requires-Dist: pyobjc-framework-SafetyKit==11.0
Requires-Dist: pyobjc-framework-SceneKit==11.0
Requires-Dist: pyobjc-framework-ScreenCaptureKit==11.0
Requires-Dist: pyobjc-framework-ScreenSaver==11.0
Requires-Dist: pyobjc-framework-ScreenTime==11.0
Requires-Dist: pyobjc-framework-ScriptingBridge==11.0
Requires-Dist: pyobjc-framework-SearchKit==11.0
Requires-Dist: pyobjc-framework-Security==11.0
Requires-Dist: pyobjc-framework-SecurityFoundation==11.0
Requires-Dist: pyobjc-framework-SecurityInterface==11.0
Requires-Dist: pyobjc-framework-SensitiveContentAnalysis==11.0
Requires-Dist: pyobjc-framework-ServiceManagement==11.0
Requires-Dist: pyobjc-framework-SharedWithYou==11.0
Requires-Dist: pyobjc-framework-SharedWithYouCore==11.0
Requires-Dist: pyobjc-framework-ShazamKit==11.0
Requires-Dist: pyobjc-framework-Social==11.0
Requires-Dist: pyobjc-framework-SoundAnalysis==11.0
Requires-Dist: pyobjc-framework-Speech==11.0
Requires-Dist: pyobjc-framework-SpriteKit==11.0
Requires-Dist: pyobjc-framework-StoreKit==11.0
Requires-Dist: pyobjc-framework-Symbols==11.0
Requires-Dist: pyobjc-framework-SyncServices==11.0
Requires-Dist: pyobjc-framework-SystemConfiguration==11.0
Requires-Dist: pyobjc-framework-SystemExtensions==11.0
Requires-Dist: pyobjc-framework-ThreadNetwork==11.0
Requires-Dist: pyobjc-framework-UniformTypeIdentifiers==11.0
Requires-Dist: pyobjc-framework-UserNotifications==11.0
Requires-Dist: pyobjc-framework-UserNotificationsUI==11.0
Requires-Dist: pyobjc-framework-VideoSubscriberAccount==11.0
Requires-Dist: pyobjc-framework-VideoToolbox==11.0
Requires-Dist: pyobjc-framework-Virtualization==11.0
Requires-Dist: pyobjc-framework-Vision==11.0
Requires-Dist: pyobjc-framework-WebKit==11.0
Requires-Dist: pyperclip==1.9.0
Requires-Dist: pyproject_hooks==1.2.0
Requires-Dist: pytest==8.3.4
Requires-Dist: PyYAML==6.0.2
Requires-Dist: readme_renderer==44.0
Requires-Dist: requests==2.32.3
Requires-Dist: requests-toolbelt==1.0.0
Requires-Dist: rfc3986==2.0.0
Requires-Dist: rich==13.9.4
Requires-Dist: sniffio==1.3.1
Requires-Dist: tokenizers==0.21.0
Requires-Dist: tqdm==4.67.1
Requires-Dist: twine==6.1.0
Requires-Dist: typing_extensions==4.12.2
Requires-Dist: urllib3==2.3.0
Provides-Extra: develop
Requires-Dist: build; extra == "develop"
Requires-Dist: twine; extra == "develop"
Requires-Dist: black; extra == "develop"
Requires-Dist: pytest; extra == "develop"
